departure/board/__init__.py
departure/board/animator.py
departure/board/board.py
departure/board/board_client.py
departure/board/board_updater.py
departure/board/commons.py
departure/board/contents.py
departure/board/data_updater.py
departure/board/departure_pb2.py
departure/board/departure_pb2_grpc.py
departure/board/movement.py
departure/board/protobuf.py
departure/board/renderer.py
departure/board/view_model.py
departure/board/fonts/6x10_condensed.bdf
departure/board/fonts/6x10_proportional.bdf
departure/cli/__init__.py
departure/cli/client.py
departure/cli/server.py
departure/cli/web.py
departure/commons/helpers.py
departure/commons/log.py
departure/provider/__init__.py
departure/provider/national_rail/__init__.py
departure/provider/national_rail/api.py
departure/provider/national_rail/cli.py
departure/provider/national_rail/commons.py
departure/provider/national_rail/data.py
departure/provider/national_rail/data_updater.py
departure/provider/national_rail/national_rail.py
departure/provider/national_rail/server.py
departure/provider/national_rail/ui.py
departure/provider/national_rail/view_model.py
departure/provider/national_rail/data/station_codes.csv
departure/provider/ns/__init__.py
departure/provider/ns/api.py
departure/provider/ns/cli.py
departure/provider/ns/commons.py
departure/provider/ns/data.py
departure/provider/ns/data_updater.py
departure/provider/ns/ns.py
departure/provider/ns/server.py
departure/provider/ns/ui.py
departure/provider/ns/view_model.py
departure/provider/ns/data/stations-2020-01-nl.csv
departure/provider/ratp/__init__.py
departure/provider/ratp/api.py
departure/provider/ratp/cli.py
departure/provider/ratp/commons.py
departure/provider/ratp/data_updater.py
departure/provider/ratp/ratp.py
departure/provider/ratp/server.py
departure/provider/ratp/ui.py
departure/provider/ratp/view_model.py
departure/provider/ratp/data/Wsiv.wsdl
departure/provider/sncf/__init__.py
departure/provider/sncf/api.py
departure/provider/sncf/cli.py
departure-1.0.1.dist-info/LICENSE
departure-1.0.1.dist-info/METADATA
departure-1.0.1.dist-info/WHEEL
departure-1.0.1.dist-info/entry_points.txt
departure-1.0.1.dist-info/top_level.txt
departure-1.0.1.dist-info/RECORD
