Metadata-Version: 2.1
Name: departure
Version: 1.0.1
Summary: Get station information and departures from public transport operators, and control virtual or physical departure boards.
Home-page: https://github.com/spujadas/departure-python
Author: Sébastien Pujadas
Author-email: sebastien@pujadas.net
License: UNKNOWN
Platform: UNKNOWN
Classifier: Programming Language :: Python :: 3
Classifier: License :: OSI Approved :: MIT License
Classifier: Operating System :: OS Independent
Requires-Python: >=3.6
Requires-Dist: requests
Requires-Dist: protobuf
Requires-Dist: grpcio
Requires-Dist: bdflib
Requires-Dist: click
Requires-Dist: uvicorn
Requires-Dist: aiofiles
Requires-Dist: zeep
Requires-Dist: fastapi
Requires-Dist: tabulate
